yaml_json_config_paco/GenericItem.py
yaml_json_config_paco/OrderedDictYaml.py
yaml_json_config_paco/Properties.py
yaml_json_config_paco/__init__.py
yaml_json_config_paco-0.1.0.dist-info/METADATA
yaml_json_config_paco-0.1.0.dist-info/WHEEL
yaml_json_config_paco-0.1.0.dist-info/licenses/LICENSE
yaml_json_config_paco-0.1.0.dist-info/RECORD
