Metadata-Version: 2.1
Name: yaml_json_config_paco
Version: 0.1.0
Summary: load yaml/json to python object or pack it back
Project-URL: Homepage, https://github.com/pacopink/py_config
Project-URL: Bug Tracker, https://github.com/pacopink/py_config/issues
Author-email: Paco Li Junting <13602887904@163.com>
License-File: LICENSE
Classifier: License :: OSI Approved :: MIT License
Classifier: Operating System :: OS Independent
Classifier: Programming Language :: Python :: 3
Requires-Python: >=3.7
Requires-Dist: pyyaml
